oadr30/__init__.py
oadr30/common.py
oadr30/config.py
oadr30/datetime_util.py
oadr30/definitions.py
oadr30/descriptors.py
oadr30/events.py
oadr30/interval.py
oadr30/log.py
oadr30/price_server_client.py
oadr30/programs.py
oadr30/resource.py
oadr30/scheduler.py
oadr30/values_map.py
oadr30/ven.py
oadr30/vtn.py
tests/__init__.py
tests/events_test.py
tests/price_server_test.py
oadr30_ven_ud-1.0.3.dist-info/LICENSE
oadr30_ven_ud-1.0.3.dist-info/METADATA
oadr30_ven_ud-1.0.3.dist-info/WHEEL
oadr30_ven_ud-1.0.3.dist-info/top_level.txt
oadr30_ven_ud-1.0.3.dist-info/RECORD
