Metadata-Version: 2.1
Name: oadr30_ven_ud
Version: 1.0.3
Summary: Open Source OpenADR 3.0 VEN Implementation
Home-page: https://github.com/universaldevices/oadr30.git
Author: Michel Kohanim
Author-email: support@universal-devices.com
Classifier: Programming Language :: Python :: 3
Classifier: License :: OSI Approved :: MIT License
Classifier: Operating System :: OS Independent
Requires-Python: >=3.9
License-File: LICENSE
Requires-Dist: requests>=2.25.1
Requires-Dist: isodate>=0.6.1
Requires-Dist: pytz>=2024.1
Requires-Dist: tzlocal>=4.2
